datadriven/__init__.py
datadriven-1.0.0.dist-info/LICENSE
datadriven-1.0.0.dist-info/METADATA
datadriven-1.0.0.dist-info/WHEEL
datadriven-1.0.0.dist-info/top_level.txt
datadriven-1.0.0.dist-info/RECORD
